mamba_clip/__init__.py
mamba_clip/data.py
mamba_clip/eval.py
mamba_clip/loss.py
mamba_clip/model.py
mamba_clip/pipeline.py
mamba_clip/sampler.py
mamba_clip/scheduler.py
mamba_clip/train.py
mamba_clip/cli/__init__.py
mamba_clip/cli/main.py
mamba_clip/utils/__init__.py
mamba_clip/utils/amp_utils.py
mamba_clip/utils/data_utils.py
mamba_clip/utils/dist_utils.py
mamba_clip/utils/file_utils.py
mamba_clip/utils/generic_utils.py
mamba_clip/utils/logging.py
mamba_clip-0.1.3.dist-info/METADATA
mamba_clip-0.1.3.dist-info/WHEEL
mamba_clip-0.1.3.dist-info/dependency_links.txt
mamba_clip-0.1.3.dist-info/entry_points.txt
mamba_clip-0.1.3.dist-info/top_level.txt
mamba_clip-0.1.3.dist-info/RECORD
